yakut/VERSION
yakut/__init__.py
yakut/__main__.py
yakut/dtype_loader.py
yakut/enum_param.py
yakut/int_set_parser.py
yakut/main.py
yakut/paths.py
yakut/register.py
yakut/subject_resolver.py
yakut/subject_specifier_processor.py
yakut/ui.py
yakut/util.py
yakut/cmd/__init__.py
yakut/cmd/accommodate.py
yakut/cmd/call.py
yakut/cmd/joystick.py
yakut/cmd/execute_command/__init__.py
yakut/cmd/execute_command/_cmd.py
yakut/cmd/file_server/__init__.py
yakut/cmd/file_server/_app_descriptor.py
yakut/cmd/file_server/_cmd.py
yakut/cmd/monitor/__init__.py
yakut/cmd/monitor/_cmd.py
yakut/cmd/monitor/_iface.py
yakut/cmd/monitor/_model.py
yakut/cmd/monitor/_ui.py
yakut/cmd/monitor/_view.py
yakut/cmd/orchestrate/__init__.py
yakut/cmd/orchestrate/_child.py
yakut/cmd/orchestrate/_env.py
yakut/cmd/orchestrate/_executor.py
yakut/cmd/orchestrate/_schema.py
yakut/cmd/publish/__init__.py
yakut/cmd/publish/_cmd.py
yakut/cmd/publish/_controller.py
yakut/cmd/publish/_executor.py
yakut/cmd/register_access/__init__.py
yakut/cmd/register_access/_cmd.py
yakut/cmd/register_access/_logic.py
yakut/cmd/register_batch/__init__.py
yakut/cmd/register_batch/_caller.py
yakut/cmd/register_batch/_cmd.py
yakut/cmd/register_batch/_directive.py
yakut/cmd/register_list/__init__.py
yakut/cmd/register_list/_cmd.py
yakut/cmd/register_list/_logic.py
yakut/cmd/subscribe/__init__.py
yakut/cmd/subscribe/_cmd.py
yakut/cmd/subscribe/_sync.py
yakut/cmd/subscribe/_sync_async.py
yakut/cmd/subscribe/_sync_monoclust.py
yakut/cmd/subscribe/_sync_transfer_id.py
yakut/controller/__init__.py
yakut/controller/joystick.py
yakut/controller/midi.py
yakut/controller/null.py
yakut/param/__init__.py
yakut/param/formatter.py
yakut/param/node.py
yakut/param/transport.py
yakut/yaml/__init__.py
yakut/yaml/_dumper.py
yakut/yaml/_eval_loader.py
yakut/yaml/_loader.py
yakut-0.14.1.dist-info/licenses/LICENSE
yakut-0.14.1.dist-info/METADATA
yakut-0.14.1.dist-info/WHEEL
yakut-0.14.1.dist-info/entry_points.txt
yakut-0.14.1.dist-info/top_level.txt
yakut-0.14.1.dist-info/RECORD
