Metadata-Version: 2.4
Name: yakut
Version: 0.14.1
Summary: Simple CLI tool for diagnostics and debugging of Cyphal networks.
Home-page: https://opencyphal.org
Author: OpenCyphal
Author-email: maintainers@opencyphal.org
License: MIT
Keywords: uavcan,data-bus,can-bus,ethernet,vehicular,onboard-networking,avionics,communication-protocol,cli,utility
Classifier: Environment :: Console
Classifier: Intended Audience :: Developers
Classifier: Intended Audience :: Customer Service
Classifier: Intended Audience :: Science/Research
Classifier: Topic :: Scientific/Engineering
Classifier: Topic :: Scientific/Engineering :: Interface Engine/Protocol Translator
Classifier: Topic :: Scientific/Engineering :: Visualization
Classifier: Topic :: Software Development :: Object Brokering
Classifier: Topic :: System :: Distributed Computing
Classifier: Topic :: System :: Networking
Classifier: Topic :: System :: Monitoring
Classifier: Topic :: Terminals
Classifier: Topic :: Utilities
Classifier: License :: OSI Approved :: MIT License
Classifier: Programming Language :: Python
Classifier: Programming Language :: Python :: 3
Classifier: Operating System :: POSIX :: Linux
Classifier: Operating System :: Microsoft :: Windows
Classifier: Operating System :: MacOS
Classifier: Typing :: Typed
License-File: LICENSE
Requires-Dist: pycyphal[transport-can-pythoncan,transport-serial,transport-udp]~=1.20
Requires-Dist: ruamel.yaml<0.18
Requires-Dist: requests~=2.27
Requires-Dist: simplejson~=3.17
Requires-Dist: coloredlogs~=15.0
Requires-Dist: click~=8.1
Requires-Dist: psutil~=5.9
Requires-Dist: scipy~=1.8
Provides-Extra: joystick
Requires-Dist: pysdl2<2.0; extra == "joystick"
Requires-Dist: pysdl2-dll~=2.0; (sys_platform == "win32" or sys_platform == "darwin") and extra == "joystick"
Requires-Dist: mido~=1.2; extra == "joystick"
Requires-Dist: python-rtmidi~=1.4; extra == "joystick"
Dynamic: license-file
